Metadata-Version: 2.1
Name: odoo14-addon-account-reconcile-payment-order
Version: 14.0.2.0.0
Summary: Automatically propose all lines generated from payment orders
Home-page: https://github.com/OCA/account-reconcile
Author: Therp BV, Tecnativa, Odoo Community Association (OCA)
Author-email: support@odoo-community.org
License: AGPL-3
Platform: UNKNOWN
Classifier: Programming Language :: Python
Classifier: Framework :: Odoo
Classifier: Framework :: Odoo :: 14.0
Classifier: License :: OSI Approved :: GNU Affero General Public License v3
Requires-Python: >=3.6
Requires-Dist: odoo14-addon-account-payment-order
Requires-Dist: odoo14-addon-account-reconciliation-widget
Requires-Dist: odoo (<14.1dev,>=14.0a)
